pre_layout/dvsd_pe.v
module dvsd_pe(in, en, out, eno, gs);
	
	input [7:0]in;
	input en;

	output reg [2:0]out;
	output eno, gs;

 assign eno = !(in & en);
 assign gs = !eno & en;
 
	always@(in, en)
	begin if (en)

casex(in)

	8'b00000001:out = 3'b000;
	8'b00000010:out = 3'b001;
	8'b00000100:out = 3'b010;
	8'b00001000:out = 3'b011;
	8'b00010000:out = 3'b100;
	8'b00100000:out = 3'b101;
	8'b01000000:out = 3'b110;
	8'b10000000:out = 3'b111;
	default:$display("Error!");

endcase
end
endmodule

pre_layout/test_dvsd_pe.v
`timescale 1ns / 1ps
module test_dvsd_pe;

	reg [7:0] in;
	reg en;
 
	wire [2:0] out;
	wire eno, gs;

 dvsd_pe uut1 (.in(in), .en(en), .out(out), .eno(eno), .gs(gs) );

initial begin
	$dumpfile("dvsd_pe.vcd");	
	$dumpvars(0,test_dvsd_pe);
	
 in = 8'b00000000; en = 0; #10;
 in = 8'b00000001; en = 1; #10;
 in = 8'b00000010; en = 1; #10;
 in = 8'b00000100; en = 1; #10;
 in = 8'b00001000; en = 1; #10;
 in = 8'b00010000; en = 1; #10;
 in = 8'b00100000; en = 1; #10;
 in = 8'b01000000; en = 1; #10;
 in = 8'b10000000; en = 1; #10;

 end
endmodule

pre_layout/dvsd_pe.vcd
$date
	Thu Aug 19 15:10:31 2021
$end
$version
	Icarus Verilog
$end
$timescale
	1ps
$end
$scope module test_dvsd_pe $end
$var wire 3 ! out [2:0] $end
$var wire 1 " gs $end
$var wire 1 # eno $end
$var reg 1 $ en $end
$var reg 8 % in [7:0] $end
$scope module uut1 $end
$var wire 1 $ en $end
$var wire 1 " gs $end
$var wire 8 & in [7:0] $end
$var wire 1 # eno $end
$var reg 3 ' out [2:0] $end
$upscope $end
$upscope $end
$enddefinitions $end
#0
$dumpvars
bx '
b0 &
b0 %
0$
1#
0"
bx !
$end
#10000
1"
0#
b0 !
b0 '
1$
b1 %
b1 &
#20000
0"
1#
b1 !
b1 '
b10 %
b10 &
#30000
b10 !
b10 '
b100 %
b100 &
#40000
b11 !
b11 '
b1000 %
b1000 &
#50000
b100 !
b100 '
b10000 %
b10000 &
#60000
b101 !
b101 '
b100000 %
b100000 &
#70000
b110 !
b110 '
b1000000 %
b1000000 &
#80000
b111 !
b111 '
b10000000 %
b10000000 &
