pre_layout_simulation/dvsd_pe.v
//  Verilog behavioral RTL code for 8-bit Priority Encoder
//  Copyright (C) 2021 Mohammad Khailique Khan
//
//  Licensed under the Apache License, Version 2.0 (the "License");
//  you may not use this file except in compliance with the License.
//  You may obtain a copy of the License at
//
//   http://www.apache.org/licenses/LICENSE-2.0
//
//  Unless required by applicable law or agreed to in writing, software
//  distributed under the License is distributed on an "AS IS" BASIS,
//  WITHOUT WARRANTIES OR CONDITIONS OF ANY KIND, either express or implied.
//  See the License for the specific language governing permissions and
//  limitations under the License. 


`default_nettype none

module dvsd_pe (en, in, eno, gs, out);

	input en;	//Enable Input
	input [7:0]in;	//8 Input line 
	
	output eno, gs;	//Enable outputs
	output reg [2:0]out;	//3 Output lines
	
	wire _a_;

// Compiling enable outputs  
 assign _a_ = ~& in ;
 assign eno = ~(_a_ & en);
 assign gs = ~eno & en;
 
always@(in, en)
	begin if (en)

		casex(in)
	
		// Default Priority set at High Impedance 
		8'b00000000:out = 3'bzzz;

		// Lowest Priority
		8'b00000001:out = 3'b000;
		8'b0000001x:out = 3'b001;
		8'b000001xx:out = 3'b010;
		8'b00001xxx:out = 3'b011;
		8'b0001xxxx:out = 3'b100;
		8'b001xxxxx:out = 3'b101;
		8'b01xxxxxx:out = 3'b110;
		8'b1xxxxxxx:out = 3'b111;
		// Highest Priority

		endcase
	end
endmodule

`default_nettype wire

pre_layout_simulation/test_dvsd_pe.v
//  Testbench for 8-bit Priority Encoder
//  Copyright (C) 2021 Mohammad Khailique Khan
//
//  Licensed under the Apache License, Version 2.0 (the "License");
//  you may not use this file except in compliance with the License.
//  You may obtain a copy of the License at
//
//   http://www.apache.org/licenses/LICENSE-2.0
//
//  Unless required by applicable law or agreed to in writing, software
//  distributed under the License is distributed on an "AS IS" BASIS,
//  WITHOUT WARRANTIES OR CONDITIONS OF ANY KIND, either express or implied.
//  See the License for the specific language governing permissions and
//  limitations under the License. 

`timescale 1ns / 1ps
`include "dvsd_pe.v"

module test_dvsd_pe;

	reg en;
	reg [7:0] in;
	
 	wire eno, gs;
	wire [2:0] out;
	

 dvsd_pe uut (.in(in), .en(en), .out(out), .eno(eno), .gs(gs) );

initial begin
	$dumpfile("dvsd_pe.vcd");	
	$dumpvars(0,test_dvsd_pe);
	
 in = 8'b00000000; en = 0; #10;
 in = 8'b00000001; en = 1; #10;
 in = 8'b00000010; en = 1; #10;
 in = 8'b00000100; en = 1; #10;
 in = 8'b00001000; en = 1; #10;
 in = 8'b00010000; en = 1; #10;
 in = 8'b00100000; en = 1; #10;
 in = 8'b01000000; en = 1; #10;
 in = 8'b10000000; en = 1; #10;

 end
endmodule

pre_layout_simulation/dvsd_pe.vcd
$date
	Fri Oct 15 09:36:48 2021
$end
$version
	Icarus Verilog
$end
$timescale
	1ps
$end
$scope module test_dvsd_pe $end
$var wire 3 ! out [2:0] $end
$var wire 1 " gs $end
$var wire 1 # eno $end
$var reg 1 $ en $end
$var reg 8 % in [7:0] $end
$scope module uut $end
$var wire 1 $ en $end
$var wire 1 # eno $end
$var wire 1 " gs $end
$var wire 8 & in [7:0] $end
$var wire 1 ' _a_ $end
$var reg 3 ( out [2:0] $end
$upscope $end
$upscope $end
$enddefinitions $end
#0
$dumpvars
bx (
1'
b0 &
b0 %
0$
1#
0"
bx !
$end
#10000
1"
0#
b0 !
b0 (
1$
b1 %
b1 &
#20000
b1 !
b1 (
b10 %
b10 &
#30000
b10 !
b10 (
b100 %
b100 &
#40000
b11 !
b11 (
b1000 %
b1000 &
#50000
b100 !
b100 (
b10000 %
b10000 &
#60000
b101 !
b101 (
b100000 %
b100000 &
#70000
b110 !
b110 (
b1000000 %
b1000000 &
#80000
b111 !
b111 (
b10000000 %
b10000000 &
